jsoninja/__init__.py
jsoninja-1.2.0.dist-info/METADATA
jsoninja-1.2.0.dist-info/WHEEL
jsoninja-1.2.0.dist-info/licenses/LICENSE
jsoninja-1.2.0.dist-info/RECORD
