Metadata-Version: 2.4
Name: jsoninja
Version: 1.2.0
Summary: Jsoninja is a library that allows you to generate JSON's from templates written with Python data types.
Project-URL: Source, https://github.com/vlazaroes/jsoninja
Author-email: Víctor Lázaro <vlazaro@outlook.es>
License: MIT License
License-File: LICENSE
Classifier: Development Status :: 5 - Production/Stable
Classifier: Environment :: Console
Classifier: Environment :: Other Environment
Classifier: Environment :: Web Environment
Classifier: Intended Audience :: Developers
Classifier: License :: OSI Approved :: MIT License
Classifier: Operating System :: OS Independent
Classifier: Programming Language :: Python
Classifier: Programming Language :: Python :: 3
Classifier: Programming Language :: Python :: 3 :: Only
Classifier: Topic :: File Formats
Classifier: Topic :: File Formats :: JSON
Classifier: Topic :: Software Development
Classifier: Topic :: Software Development :: Libraries
Classifier: Topic :: Software Development :: Libraries :: Python Modules
Classifier: Typing :: Typed
Requires-Python: >=3.8
